{
  "en_st": 5,
  "en_naz": "Celje",
  "st": 2,
  "naz": "Celje 1",
  "vol": [
    {
      "st": 56,
      "naz": "AVTO ČEPIN, POT V LEŠJE 1",
      "udel": {
        "upr": 418,
        "gl": 313,
        "prc": 0.7488
      },
      "rez": {
        "rez": [
          {
            "st": 1,
            "gl": 2,
            "prc": 0.0064
          },
          {
            "st": 2,
            "gl": 1,
            "prc": 0.0032
          },
          {
            "st": 3,
            "gl": 4,
            "prc": 0.0129
          },
          {
            "st": 4,
            "gl": 85,
            "prc": 0.2733
          },
          {
            "st": 5,
            "gl": 0,
            "prc": null
          },
          {
            "st": 6,
            "gl": 8,
            "prc": 0.0257
          },
          {
            "st": 7,
            "gl": 0,
            "prc": 0
          },
          {
            "st": 8,
            "gl": 4,
            "prc": 0.0129
          },
          {
            "st": 9,
            "gl": 5,
            "prc": 0.0161
          },
          {
            "st": 10,
            "gl": 6,
            "prc": 0.0193
          },
          {
            "st": 11,
            "gl": 2,
            "prc": 0.0064
          },
          {
            "st": 12,
            "gl": 36,
            "prc": 0.1158
          },
          {
            "st": 13,
            "gl": 3,
            "prc": 0.0096
          },
          {
            "st": 14,
            "gl": 17,
            "prc": 0.0547
          },
          {
            "st": 15,
            "gl": 99,
            "prc": 0.3183
          },
          {
            "st": 16,
            "gl": 13,
            "prc": 0.0418
          },
          {
            "st": 17,
            "gl": 13,
            "prc": 0.0418
          },
          {
            "st": 18,
            "gl": 10,
            "prc": 0.0322
          },
          {
            "st": 19,
            "gl": 1,
            "prc": 0.0032
          },
          {
            "st": 20,
            "gl": 2,
            "prc": 0.0064
          },
          {
            "st": 21,
            "gl": 0,
            "prc": null
          }
        ],
        "glas": 313,
        "velj": 311,
        "nev": 2
      },
      "prestetih_glasov": 1
    },
    {
      "st": 13,
      "naz": "DOM KRAJANOV, ŠMARTNO V ROŽNI DOLINI 5",
      "udel": {
        "upr": 1789,
        "gl": 978,
        "prc": 0.5467
      },
      "rez": {
        "rez": [
          {
            "st": 1,
            "gl": 0,
            "prc": null
          },
          {
            "st": 2,
            "gl": 0,
            "prc": null
          },
          {
            "st": 3,
            "gl": 0,
            "prc": null
          },
          {
            "st": 4,
            "gl": 0,
            "prc": null
          },
          {
            "st": 5,
            "gl": 0,
            "prc": null
          },
          {
            "st": 6,
            "gl": 0,
            "prc": null
          },
          {
            "st": 7,
            "gl": 0,
            "prc": null
          },
          {
            "st": 8,
            "gl": 0,
            "prc": null
          },
          {
            "st": 9,
            "gl": 0,
            "prc": null
          },
          {
            "st": 10,
            "gl": 0,
            "prc": null
          },
          {
            "st": 11,
            "gl": 0,
            "prc": null
          },
          {
            "st": 12,
            "gl": 0,
            "prc": null
          },
          {
            "st": 13,
            "gl": 0,
            "prc": null
          },
          {
            "st": 14,
            "gl": 0,
            "prc": null
          },
          {
            "st": 15,
            "gl": 0,
            "prc": null
          },
          {
            "st": 16,
            "gl": 0,
            "prc": null
          },
          {
            "st": 17,
            "gl": 0,
            "prc": null
          },
          {
            "st": 18,
            "gl": 0,
            "prc": null
          },
          {
            "st": 19,
            "gl": 0,
            "prc": null
          },
          {
            "st": 20,
            "gl": 0,
            "prc": null
          },
          {
            "st": 21,
            "gl": 0,
            "prc": null
          }
        ],
        "glas": 0,
        "velj": 0,
        "nev": 0
      },
      "prestetih_glasov": 0
    },
    {
      "st": 19,
      "naz": "DOM KS LJUBEČNA",
      "udel": {
        "upr": 1324,
        "gl": 883,
        "prc": 0.6669
      },
      "rez": {
        "rez": [
          {
            "st": 1,
            "gl": 6,
            "prc": 0.0069
          },
          {
            "st": 2,
            "gl": 0,
            "prc": 0
          },
          {
            "st": 3,
            "gl": 39,
            "prc": 0.0447
          },
          {
            "st": 4,
            "gl": 288,
            "prc": 0.3303
          },
          {
            "st": 5,
            "gl": 0,
            "prc": null
          },
          {
            "st": 6,
            "gl": 13,
            "prc": 0.0149
          },
          {
            "st": 7,
            "gl": 0,
            "prc": 0
          },
          {
            "st": 8,
            "gl": 18,
            "prc": 0.0206
          },
          {
            "st": 9,
            "gl": 13,
            "prc": 0.0149
          },
          {
            "st": 10,
            "gl": 19,
            "prc": 0.0218
          },
          {
            "st": 11,
            "gl": 14,
            "prc": 0.0161
          },
          {
            "st": 12,
            "gl": 48,
            "prc": 0.055
          },
          {
            "st": 13,
            "gl": 7,
            "prc": 0.008
          },
          {
            "st": 14,
            "gl": 44,
            "prc": 0.0505
          },
          {
            "st": 15,
            "gl": 265,
            "prc": 0.3039
          },
          {
            "st": 16,
            "gl": 22,
            "prc": 0.0252
          },
          {
            "st": 17,
            "gl": 39,
            "prc": 0.0447
          },
          {
            "st": 18,
            "gl": 18,
            "prc": 0.0206
          },
          {
            "st": 19,
            "gl": 8,
            "prc": 0.0092
          },
          {
            "st": 20,
            "gl": 11,
            "prc": 0.0126
          },
          {
            "st": 21,
            "gl": 0,
            "prc": null
          }
        ],
        "glas": 883,
        "velj": 872,
        "nev": 11
      },
      "prestetih_glasov": 1
    },
    {
      "st": 6,
      "naz": "DVORANA KS TEHARJE, TEHARJE 14",
      "udel": {
        "upr": 278,
        "gl": 182,
        "prc": 0.6547
      },
      "rez": {
        "rez": [
          {
            "st": 1,
            "gl": 0,
            "prc": 0
          },
          {
            "st": 2,
            "gl": 0,
            "prc": 0
          },
          {
            "st": 3,
            "gl": 6,
            "prc": 0.0331
          },
          {
            "st": 4,
            "gl": 55,
            "prc": 0.3039
          },
          {
            "st": 5,
            "gl": 0,
            "prc": null
          },
          {
            "st": 6,
            "gl": 6,
            "prc": 0.0331
          },
          {
            "st": 7,
            "gl": 0,
            "prc": 0
          },
          {
            "st": 8,
            "gl": 4,
            "prc": 0.0221
          },
          {
            "st": 9,
            "gl": 1,
            "prc": 0.0055
          },
          {
            "st": 10,
            "gl": 10,
            "prc": 0.0552
          },
          {
            "st": 11,
            "gl": 0,
            "prc": 0
          },
          {
            "st": 12,
            "gl": 10,
            "prc": 0.0552
          },
          {
            "st": 13,
            "gl": 6,
            "prc": 0.0331
          },
          {
            "st": 14,
            "gl": 10,
            "prc": 0.0552
          },
          {
            "st": 15,
            "gl": 51,
            "prc": 0.2818
          },
          {
            "st": 16,
            "gl": 5,
            "prc": 0.0276
          },
          {
            "st": 17,
            "gl": 14,
            "prc": 0.0773
          },
          {
            "st": 18,
            "gl": 2,
            "prc": 0.011
          },
          {
            "st": 19,
            "gl": 1,
            "prc": 0.0055
          },
          {
            "st": 20,
            "gl": 0,
            "prc": 0
          },
          {
            "st": 21,
            "gl": 0,
            "prc": null
          }
        ],
        "glas": 182,
        "velj": 181,
        "nev": 1
      },
      "prestetih_glasov": 1
    },
    {
      "st": 40,
      "naz": "GASILSKI DOM FRANKOLOVO,STRAŽICA 2",
      "udel": {
        "upr": 577,
        "gl": 307,
        "prc": 0.5321
      },
      "rez": {
        "rez": [
          {
            "st": 1,
            "gl": 0,
            "prc": null
          },
          {
            "st": 2,
            "gl": 0,
            "prc": null
          },
          {
            "st": 3,
            "gl": 0,
            "prc": null
          },
          {
            "st": 4,
            "gl": 0,
            "prc": null
          },
          {
            "st": 5,
            "gl": 0,
            "prc": null
          },
          {
            "st": 6,
            "gl": 0,
            "prc": null
          },
          {
            "st": 7,
            "gl": 0,
            "prc": null
          },
          {
            "st": 8,
            "gl": 0,
            "prc": null
          },
          {
            "st": 9,
            "gl": 0,
            "prc": null
          },
          {
            "st": 10,
            "gl": 0,
            "prc": null
          },
          {
            "st": 11,
            "gl": 0,
            "prc": null
          },
          {
            "st": 12,
            "gl": 0,
            "prc": null
          },
          {
            "st": 13,
            "gl": 0,
            "prc": null
          },
          {
            "st": 14,
            "gl": 0,
            "prc": null
          },
          {
            "st": 15,
            "gl": 0,
            "prc": null
          },
          {
            "st": 16,
            "gl": 0,
            "prc": null
          },
          {
            "st": 17,
            "gl": 0,
            "prc": null
          },
          {
            "st": 18,
            "gl": 0,
            "prc": null
          },
          {
            "st": 19,
            "gl": 0,
            "prc": null
          },
          {
            "st": 20,
            "gl": 0,
            "prc": null
          },
          {
            "st": 21,
            "gl": 0,
            "prc": null
          }
        ],
        "glas": 0,
        "velj": 0,
        "nev": 0
      },
      "prestetih_glasov": 0
    },
    {
      "st": 47,
      "naz": "GASILSKI DOM LEMBERG",
      "udel": {
        "upr": 267,
        "gl": 185,
        "prc": 0.6929
      },
      "rez": {
        "rez": [
          {
            "st": 1,
            "gl": 1,
            "prc": 0.0056
          },
          {
            "st": 2,
            "gl": 0,
            "prc": 0
          },
          {
            "st": 3,
            "gl": 6,
            "prc": 0.0333
          },
          {
            "st": 4,
            "gl": 35,
            "prc": 0.1944
          },
          {
            "st": 5,
            "gl": 0,
            "prc": null
          },
          {
            "st": 6,
            "gl": 0,
            "prc": 0
          },
          {
            "st": 7,
            "gl": 0,
            "prc": 0
          },
          {
            "st": 8,
            "gl": 6,
            "prc": 0.0333
          },
          {
            "st": 9,
            "gl": 1,
            "prc": 0.0056
          },
          {
            "st": 10,
            "gl": 2,
            "prc": 0.0111
          },
          {
            "st": 11,
            "gl": 0,
            "prc": 0
          },
          {
            "st": 12,
            "gl": 10,
            "prc": 0.0556
          },
          {
            "st": 13,
            "gl": 2,
            "prc": 0.0111
          },
          {
            "st": 14,
            "gl": 7,
            "prc": 0.0389
          },
          {
            "st": 15,
            "gl": 94,
            "prc": 0.5222
          },
          {
            "st": 16,
            "gl": 4,
            "prc": 0.0222
          },
          {
            "st": 17,
            "gl": 7,
            "prc": 0.0389
          },
          {
            "st": 18,
            "gl": 3,
            "prc": 0.0167
          },
          {
            "st": 19,
            "gl": 2,
            "prc": 0.0111
          },
          {
            "st": 20,
            "gl": 0,
            "prc": 0
          },
          {
            "st": 21,
            "gl": 0,
            "prc": null
          }
        ],
        "glas": 185,
        "velj": 180,
        "nev": 5
      },
      "prestetih_glasov": 1
    },
    {
      "st": 11,
      "naz": "GASILSKI DOM LOKROVEC",
      "udel": {
        "upr": 280,
        "gl": 182,
        "prc": 0.65
      },
      "rez": {
        "rez": [
          {
            "st": 1,
            "gl": 2,
            "prc": 0.011
          },
          {
            "st": 2,
            "gl": 0,
            "prc": 0
          },
          {
            "st": 3,
            "gl": 6,
            "prc": 0.0331
          },
          {
            "st": 4,
            "gl": 40,
            "prc": 0.221
          },
          {
            "st": 5,
            "gl": 0,
            "prc": null
          },
          {
            "st": 6,
            "gl": 9,
            "prc": 0.0497
          },
          {
            "st": 7,
            "gl": 0,
            "prc": 0
          },
          {
            "st": 8,
            "gl": 11,
            "prc": 0.0608
          },
          {
            "st": 9,
            "gl": 5,
            "prc": 0.0276
          },
          {
            "st": 10,
            "gl": 3,
            "prc": 0.0166
          },
          {
            "st": 11,
            "gl": 3,
            "prc": 0.0166
          },
          {
            "st": 12,
            "gl": 5,
            "prc": 0.0276
          },
          {
            "st": 13,
            "gl": 5,
            "prc": 0.0276
          },
          {
            "st": 14,
            "gl": 20,
            "prc": 0.1105
          },
          {
            "st": 15,
            "gl": 57,
            "prc": 0.3149
          },
          {
            "st": 16,
            "gl": 5,
            "prc": 0.0276
          },
          {
            "st": 17,
            "gl": 3,
            "prc": 0.0166
          },
          {
            "st": 18,
            "gl": 4,
            "prc": 0.0221
          },
          {
            "st": 19,
            "gl": 1,
            "prc": 0.0055
          },
          {
            "st": 20,
            "gl": 2,
            "prc": 0.011
          },
          {
            "st": 21,
            "gl": 0,
            "prc": null
          }
        ],
        "glas": 182,
        "velj": 181,
        "nev": 1
      },
      "prestetih_glasov": 1
    },
    {
      "st": 10,
      "naz": "GASILSKI DOM LOPATA",
      "udel": {
        "upr": 513,
        "gl": 333,
        "prc": 0.6491
      },
      "rez": {
        "rez": [
          {
            "st": 1,
            "gl": 6,
            "prc": 0.0183
          },
          {
            "st": 2,
            "gl": 1,
            "prc": 0.003
          },
          {
            "st": 3,
            "gl": 10,
            "prc": 0.0305
          },
          {
            "st": 4,
            "gl": 115,
            "prc": 0.3506
          },
          {
            "st": 5,
            "gl": 0,
            "prc": null
          },
          {
            "st": 6,
            "gl": 8,
            "prc": 0.0244
          },
          {
            "st": 7,
            "gl": 0,
            "prc": 0
          },
          {
            "st": 8,
            "gl": 5,
            "prc": 0.0152
          },
          {
            "st": 9,
            "gl": 5,
            "prc": 0.0152
          },
          {
            "st": 10,
            "gl": 5,
            "prc": 0.0152
          },
          {
            "st": 11,
            "gl": 8,
            "prc": 0.0244
          },
          {
            "st": 12,
            "gl": 28,
            "prc": 0.0854
          },
          {
            "st": 13,
            "gl": 4,
            "prc": 0.0122
          },
          {
            "st": 14,
            "gl": 27,
            "prc": 0.0823
          },
          {
            "st": 15,
            "gl": 71,
            "prc": 0.2165
          },
          {
            "st": 16,
            "gl": 10,
            "prc": 0.0305
          },
          {
            "st": 17,
            "gl": 12,
            "prc": 0.0366
          },
          {
            "st": 18,
            "gl": 5,
            "prc": 0.0152
          },
          {
            "st": 19,
            "gl": 3,
            "prc": 0.0091
          },
          {
            "st": 20,
            "gl": 5,
            "prc": 0.0152
          },
          {
            "st": 21,
            "gl": 0,
            "prc": null
          }
        ],
        "glas": 333,
        "velj": 328,
        "nev": 5
      },
      "prestetih_glasov": 1
    },
    {
      "st": 9,
      "naz": "GASILSKI DOM OSTROŽNO",
      "udel": {
        "upr": 1550,
        "gl": 1099,
        "prc": 0.709
      },
      "rez": {
        "rez": [
          {
            "st": 1,
            "gl": 7,
            "prc": 0.0064
          },
          {
            "st": 2,
            "gl": 2,
            "prc": 0.0018
          },
          {
            "st": 3,
            "gl": 16,
            "prc": 0.0147
          },
          {
            "st": 4,
            "gl": 469,
            "prc": 0.4295
          },
          {
            "st": 5,
            "gl": 0,
            "prc": null
          },
          {
            "st": 6,
            "gl": 41,
            "prc": 0.0375
          },
          {
            "st": 7,
            "gl": 4,
            "prc": 0.0037
          },
          {
            "st": 8,
            "gl": 26,
            "prc": 0.0238
          },
          {
            "st": 9,
            "gl": 11,
            "prc": 0.0101
          },
          {
            "st": 10,
            "gl": 15,
            "prc": 0.0137
          },
          {
            "st": 11,
            "gl": 9,
            "prc": 0.0082
          },
          {
            "st": 12,
            "gl": 54,
            "prc": 0.0495
          },
          {
            "st": 13,
            "gl": 20,
            "prc": 0.0183
          },
          {
            "st": 14,
            "gl": 48,
            "prc": 0.044
          },
          {
            "st": 15,
            "gl": 218,
            "prc": 0.1996
          },
          {
            "st": 16,
            "gl": 14,
            "prc": 0.0128
          },
          {
            "st": 17,
            "gl": 76,
            "prc": 0.0696
          },
          {
            "st": 18,
            "gl": 44,
            "prc": 0.0403
          },
          {
            "st": 19,
            "gl": 12,
            "prc": 0.011
          },
          {
            "st": 20,
            "gl": 6,
            "prc": 0.0055
          },
          {
            "st": 21,
            "gl": 0,
            "prc": null
          }
        ],
        "glas": 1099,
        "velj": 1092,
        "nev": 7
      },
      "prestetih_glasov": 1
    },
    {
      "st": 24,
      "naz": "GASILSKI DOM PROŽINSKA VAS,PROŽINSKA VAS 33,ŠTORE",
      "udel": {
        "upr": 464,
        "gl": 327,
        "prc": 0.7047
      },
      "rez": {
        "rez": [
          {
            "st": 1,
            "gl": 3,
            "prc": 0.0092
          },
          {
            "st": 2,
            "gl": 0,
            "prc": 0
          },
          {
            "st": 3,
            "gl": 14,
            "prc": 0.0429
          },
          {
            "st": 4,
            "gl": 98,
            "prc": 0.3006
          },
          {
            "st": 5,
            "gl": 0,
            "prc": null
          },
          {
            "st": 6,
            "gl": 1,
            "prc": 0.0031
          },
          {
            "st": 7,
            "gl": 0,
            "prc": 0
          },
          {
            "st": 8,
            "gl": 6,
            "prc": 0.0184
          },
          {
            "st": 9,
            "gl": 6,
            "prc": 0.0184
          },
          {
            "st": 10,
            "gl": 4,
            "prc": 0.0123
          },
          {
            "st": 11,
            "gl": 4,
            "prc": 0.0123
          },
          {
            "st": 12,
            "gl": 16,
            "prc": 0.0491
          },
          {
            "st": 13,
            "gl": 7,
            "prc": 0.0215
          },
          {
            "st": 14,
            "gl": 20,
            "prc": 0.0613
          },
          {
            "st": 15,
            "gl": 108,
            "prc": 0.3313
          },
          {
            "st": 16,
            "gl": 9,
            "prc": 0.0276
          },
          {
            "st": 17,
            "gl": 25,
            "prc": 0.0767
          },
          {
            "st": 18,
            "gl": 3,
            "prc": 0.0092
          },
          {
            "st": 19,
            "gl": 1,
            "prc": 0.0031
          },
          {
            "st": 20,
            "gl": 1,
            "prc": 0.0031
          },
          {
            "st": 21,
            "gl": 0,
            "prc": null
          }
        ],
        "glas": 327,
        "velj": 326,
        "nev": 1
      },
      "prestetih_glasov": 1
    },
    {
      "st": 32,
      "naz": "GASILSKI DOM SVETINA",
      "udel": {
        "upr": 362,
        "gl": 225,
        "prc": 0.6215
      },
      "rez": {
        "rez": [
          {
            "st": 1,
            "gl": 1,
            "prc": 0.0045
          },
          {
            "st": 2,
            "gl": 0,
            "prc": 0
          },
          {
            "st": 3,
            "gl": 9,
            "prc": 0.0405
          },
          {
            "st": 4,
            "gl": 54,
            "prc": 0.2432
          },
          {
            "st": 5,
            "gl": 0,
            "prc": null
          },
          {
            "st": 6,
            "gl": 7,
            "prc": 0.0315
          },
          {
            "st": 7,
            "gl": 0,
            "prc": 0
          },
          {
            "st": 8,
            "gl": 3,
            "prc": 0.0135
          },
          {
            "st": 9,
            "gl": 4,
            "prc": 0.018
          },
          {
            "st": 10,
            "gl": 3,
            "prc": 0.0135
          },
          {
            "st": 11,
            "gl": 3,
            "prc": 0.0135
          },
          {
            "st": 12,
            "gl": 10,
            "prc": 0.045
          },
          {
            "st": 13,
            "gl": 3,
            "prc": 0.0135
          },
          {
            "st": 14,
            "gl": 6,
            "prc": 0.027
          },
          {
            "st": 15,
            "gl": 89,
            "prc": 0.4009
          },
          {
            "st": 16,
            "gl": 5,
            "prc": 0.0225
          },
          {
            "st": 17,
            "gl": 16,
            "prc": 0.0721
          },
          {
            "st": 18,
            "gl": 5,
            "prc": 0.0225
          },
          {
            "st": 19,
            "gl": 0,
            "prc": 0
          },
          {
            "st": 20,
            "gl": 4,
            "prc": 0.018
          },
          {
            "st": 21,
            "gl": 0,
            "prc": null
          }
        ],
        "glas": 225,
        "velj": 222,
        "nev": 3
      },
      "prestetih_glasov": 1
    },
    {
      "st": 30,
      "naz": "GOBEC DRAGO, ŠENTJANŽ NAD ŠTORAMI 26",
      "udel": {
        "upr": 177,
        "gl": 122,
        "prc": 0.6893
      },
      "rez": {
        "rez": [
          {
            "st": 1,
            "gl": 2,
            "prc": 0.0165
          },
          {
            "st": 2,
            "gl": 0,
            "prc": 0
          },
          {
            "st": 3,
            "gl": 4,
            "prc": 0.0331
          },
          {
            "st": 4,
            "gl": 23,
            "prc": 0.1901
          },
          {
            "st": 5,
            "gl": 0,
            "prc": null
          },
          {
            "st": 6,
            "gl": 1,
            "prc": 0.0083
          },
          {
            "st": 7,
            "gl": 0,
            "prc": 0
          },
          {
            "st": 8,
            "gl": 13,
            "prc": 0.1074
          },
          {
            "st": 9,
            "gl": 3,
            "prc": 0.0248
          },
          {
            "st": 10,
            "gl": 6,
            "prc": 0.0496
          },
          {
            "st": 11,
            "gl": 0,
            "prc": 0
          },
          {
            "st": 12,
            "gl": 8,
            "prc": 0.0661
          },
          {
            "st": 13,
            "gl": 4,
            "prc": 0.0331
          },
          {
            "st": 14,
            "gl": 2,
            "prc": 0.0165
          },
          {
            "st": 15,
            "gl": 40,
            "prc": 0.3306
          },
          {
            "st": 16,
            "gl": 7,
            "prc": 0.0579
          },
          {
            "st": 17,
            "gl": 7,
            "prc": 0.0579
          },
          {
            "st": 18,
            "gl": 0,
            "prc": 0
          },
          {
            "st": 19,
            "gl": 0,
            "prc": 0
          },
          {
            "st": 20,
            "gl": 1,
            "prc": 0.0083
          },
          {
            "st": 21,
            "gl": 0,
            "prc": null
          }
        ],
        "glas": 122,
        "velj": 121,
        "nev": 1
      },
      "prestetih_glasov": 1
    },
    {
      "st": 15,
      "naz": "GOSTILNA TEPEŽ, RUNTOLE 3",
      "udel": {
        "upr": 357,
        "gl": 233,
        "prc": 0.6527
      },
      "rez": {
        "rez": [
          {
            "st": 1,
            "gl": 1,
            "prc": 0.0043
          },
          {
            "st": 2,
            "gl": 2,
            "prc": 0.0086
          },
          {
            "st": 3,
            "gl": 6,
            "prc": 0.0259
          },
          {
            "st": 4,
            "gl": 80,
            "prc": 0.3448
          },
          {
            "st": 5,
            "gl": 0,
            "prc": null
          },
          {
            "st": 6,
            "gl": 13,
            "prc": 0.056
          },
          {
            "st": 7,
            "gl": 1,
            "prc": 0.0043
          },
          {
            "st": 8,
            "gl": 3,
            "prc": 0.0129
          },
          {
            "st": 9,
            "gl": 0,
            "prc": 0
          },
          {
            "st": 10,
            "gl": 4,
            "prc": 0.0172
          },
          {
            "st": 11,
            "gl": 4,
            "prc": 0.0172
          },
          {
            "st": 12,
            "gl": 6,
            "prc": 0.0259
          },
          {
            "st": 13,
            "gl": 2,
            "prc": 0.0086
          },
          {
            "st": 14,
            "gl": 11,
            "prc": 0.0474
          },
          {
            "st": 15,
            "gl": 64,
            "prc": 0.2759
          },
          {
            "st": 16,
            "gl": 4,
            "prc": 0.0172
          },
          {
            "st": 17,
            "gl": 15,
            "prc": 0.0647
          },
          {
            "st": 18,
            "gl": 9,
            "prc": 0.0388
          },
          {
            "st": 19,
            "gl": 5,
            "prc": 0.0216
          },
          {
            "st": 20,
            "gl": 2,
            "prc": 0.0086
          },
          {
            "st": 21,
            "gl": 0,
            "prc": null
          }
        ],
        "glas": 233,
        "velj": 232,
        "nev": 1
      },
      "prestetih_glasov": 1
    },
    {
      "st": 4,
      "naz": "HRASTNIK MIROSLAV, VRHE 42",
      "udel": {
        "upr": 202,
        "gl": 156,
        "prc": 0.7723
      },
      "rez": {
        "rez": [
          {
            "st": 1,
            "gl": 1,
            "prc": 0.0065
          },
          {
            "st": 2,
            "gl": 0,
            "prc": 0
          },
          {
            "st": 3,
            "gl": 6,
            "prc": 0.039
          },
          {
            "st": 4,
            "gl": 34,
            "prc": 0.2208
          },
          {
            "st": 5,
            "gl": 0,
            "prc": null
          },
          {
            "st": 6,
            "gl": 5,
            "prc": 0.0325
          },
          {
            "st": 7,
            "gl": 0,
            "prc": 0
          },
          {
            "st": 8,
            "gl": 2,
            "prc": 0.013
          },
          {
            "st": 9,
            "gl": 0,
            "prc": 0
          },
          {
            "st": 10,
            "gl": 3,
            "prc": 0.0195
          },
          {
            "st": 11,
            "gl": 1,
            "prc": 0.0065
          },
          {
            "st": 12,
            "gl": 4,
            "prc": 0.026
          },
          {
            "st": 13,
            "gl": 3,
            "prc": 0.0195
          },
          {
            "st": 14,
            "gl": 6,
            "prc": 0.039
          },
          {
            "st": 15,
            "gl": 58,
            "prc": 0.3766
          },
          {
            "st": 16,
            "gl": 7,
            "prc": 0.0455
          },
          {
            "st": 17,
            "gl": 12,
            "prc": 0.0779
          },
          {
            "st": 18,
            "gl": 7,
            "prc": 0.0455
          },
          {
            "st": 19,
            "gl": 3,
            "prc": 0.0195
          },
          {
            "st": 20,
            "gl": 2,
            "prc": 0.013
          },
          {
            "st": 21,
            "gl": 0,
            "prc": null
          }
        ],
        "glas": 156,
        "velj": 154,
        "nev": 2
      },
      "prestetih_glasov": 1
    },
    {
      "st": 23,
      "naz": "IV. OSNOVNA ŠOLA, DEČKOVA CESTA 60",
      "udel": {
        "upr": 2768,
        "gl": 1613,
        "prc": 0.5827
      },
      "rez": {
        "rez": [
          {
            "st": 1,
            "gl": 9,
            "prc": 0.0056
          },
          {
            "st": 2,
            "gl": 2,
            "prc": 0.0012
          },
          {
            "st": 3,
            "gl": 88,
            "prc": 0.0549
          },
          {
            "st": 4,
            "gl": 624,
            "prc": 0.3893
          },
          {
            "st": 5,
            "gl": 0,
            "prc": null
          },
          {
            "st": 6,
            "gl": 85,
            "prc": 0.053
          },
          {
            "st": 7,
            "gl": 12,
            "prc": 0.0075
          },
          {
            "st": 8,
            "gl": 61,
            "prc": 0.0381
          },
          {
            "st": 9,
            "gl": 10,
            "prc": 0.0062
          },
          {
            "st": 10,
            "gl": 45,
            "prc": 0.0281
          },
          {
            "st": 11,
            "gl": 26,
            "prc": 0.0162
          },
          {
            "st": 12,
            "gl": 50,
            "prc": 0.0312
          },
          {
            "st": 13,
            "gl": 39,
            "prc": 0.0243
          },
          {
            "st": 14,
            "gl": 55,
            "prc": 0.0343
          },
          {
            "st": 15,
            "gl": 299,
            "prc": 0.1865
          },
          {
            "st": 16,
            "gl": 29,
            "prc": 0.0181
          },
          {
            "st": 17,
            "gl": 101,
            "prc": 0.063
          },
          {
            "st": 18,
            "gl": 34,
            "prc": 0.0212
          },
          {
            "st": 19,
            "gl": 22,
            "prc": 0.0137
          },
          {
            "st": 20,
            "gl": 12,
            "prc": 0.0075
          },
          {
            "st": 21,
            "gl": 0,
            "prc": null
          }
        ],
        "glas": 1613,
        "velj": 1603,
        "nev": 10
      },
      "prestetih_glasov": 1
    },
    {
      "st": 38,
      "naz": "KARO JANEZ, LINDEK 7 ",
      "udel": {
        "upr": 109,
        "gl": 73,
        "prc": 0.6697
      },
      "rez": {
        "rez": [
          {
            "st": 1,
            "gl": 0,
            "prc": 0
          },
          {
            "st": 2,
            "gl": 0,
            "prc": 0
          },
          {
            "st": 3,
            "gl": 7,
            "prc": 0.0972
          },
          {
            "st": 4,
            "gl": 9,
            "prc": 0.125
          },
          {
            "st": 5,
            "gl": 0,
            "prc": null
          },
          {
            "st": 6,
            "gl": 0,
            "prc": 0
          },
          {
            "st": 7,
            "gl": 0,
            "prc": 0
          },
          {
            "st": 8,
            "gl": 0,
            "prc": 0
          },
          {
            "st": 9,
            "gl": 1,
            "prc": 0.0139
          },
          {
            "st": 10,
            "gl": 0,
            "prc": 0
          },
          {
            "st": 11,
            "gl": 5,
            "prc": 0.0694
          },
          {
            "st": 12,
            "gl": 8,
            "prc": 0.1111
          },
          {
            "st": 13,
            "gl": 1,
            "prc": 0.0139
          },
          {
            "st": 14,
            "gl": 4,
            "prc": 0.0556
          },
          {
            "st": 15,
            "gl": 30,
            "prc": 0.4167
          },
          {
            "st": 16,
            "gl": 2,
            "prc": 0.0278
          },
          {
            "st": 17,
            "gl": 2,
            "prc": 0.0278
          },
          {
            "st": 18,
            "gl": 0,
            "prc": 0
          },
          {
            "st": 19,
            "gl": 3,
            "prc": 0.0417
          },
          {
            "st": 20,
            "gl": 0,
            "prc": 0
          },
          {
            "st": 21,
            "gl": 0,
            "prc": null
          }
        ],
        "glas": 73,
        "velj": 72,
        "nev": 1
      },
      "prestetih_glasov": 1
    },
    {
      "st": 12,
      "naz": "KLENOVŠEK J., DOBROVA 16",
      "udel": {
        "upr": 607,
        "gl": 431,
        "prc": 0.71
      },
      "rez": {
        "rez": [
          {
            "st": 1,
            "gl": 0,
            "prc": 0
          },
          {
            "st": 2,
            "gl": 0,
            "prc": 0
          },
          {
            "st": 3,
            "gl": 15,
            "prc": 0.035
          },
          {
            "st": 4,
            "gl": 148,
            "prc": 0.345
          },
          {
            "st": 5,
            "gl": 0,
            "prc": null
          },
          {
            "st": 6,
            "gl": 15,
            "prc": 0.035
          },
          {
            "st": 7,
            "gl": 4,
            "prc": 0.0093
          },
          {
            "st": 8,
            "gl": 19,
            "prc": 0.0443
          },
          {
            "st": 9,
            "gl": 6,
            "prc": 0.014
          },
          {
            "st": 10,
            "gl": 8,
            "prc": 0.0186
          },
          {
            "st": 11,
            "gl": 5,
            "prc": 0.0117
          },
          {
            "st": 12,
            "gl": 22,
            "prc": 0.0513
          },
          {
            "st": 13,
            "gl": 4,
            "prc": 0.0093
          },
          {
            "st": 14,
            "gl": 21,
            "prc": 0.049
          },
          {
            "st": 15,
            "gl": 103,
            "prc": 0.2401
          },
          {
            "st": 16,
            "gl": 10,
            "prc": 0.0233
          },
          {
            "st": 17,
            "gl": 22,
            "prc": 0.0513
          },
          {
            "st": 18,
            "gl": 10,
            "prc": 0.0233
          },
          {
            "st": 19,
            "gl": 11,
            "prc": 0.0256
          },
          {
            "st": 20,
            "gl": 6,
            "prc": 0.014
          },
          {
            "st": 21,
            "gl": 0,
            "prc": null
          }
        ],
        "glas": 431,
        "velj": 429,
        "nev": 2
      },
      "prestetih_glasov": 1
    },
    {
      "st": 36,
      "naz": "KRAČUN MARTIN, BEZENŠKOVO BUKOVJE 9 A",
      "udel": {
        "upr": 385,
        "gl": 274,
        "prc": 0.7117
      },
      "rez": {
        "rez": [
          {
            "st": 1,
            "gl": 1,
            "prc": 0.0037
          },
          {
            "st": 2,
            "gl": 1,
            "prc": 0.0037
          },
          {
            "st": 3,
            "gl": 8,
            "prc": 0.0294
          },
          {
            "st": 4,
            "gl": 40,
            "prc": 0.1471
          },
          {
            "st": 5,
            "gl": 0,
            "prc": null
          },
          {
            "st": 6,
            "gl": 4,
            "prc": 0.0147
          },
          {
            "st": 7,
            "gl": 0,
            "prc": 0
          },
          {
            "st": 8,
            "gl": 10,
            "prc": 0.0368
          },
          {
            "st": 9,
            "gl": 3,
            "prc": 0.011
          },
          {
            "st": 10,
            "gl": 3,
            "prc": 0.011
          },
          {
            "st": 11,
            "gl": 3,
            "prc": 0.011
          },
          {
            "st": 12,
            "gl": 20,
            "prc": 0.0735
          },
          {
            "st": 13,
            "gl": 7,
            "prc": 0.0257
          },
          {
            "st": 14,
            "gl": 3,
            "prc": 0.011
          },
          {
            "st": 15,
            "gl": 136,
            "prc": 0.5
          },
          {
            "st": 16,
            "gl": 17,
            "prc": 0.0625
          },
          {
            "st": 17,
            "gl": 8,
            "prc": 0.0294
          },
          {
            "st": 18,
            "gl": 5,
            "prc": 0.0184
          },
          {
            "st": 19,
            "gl": 1,
            "prc": 0.0037
          },
          {
            "st": 20,
            "gl": 2,
            "prc": 0.0074
          },
          {
            "st": 21,
            "gl": 0,
            "prc": null
          }
        ],
        "glas": 274,
        "velj": 272,
        "nev": 2
      },
      "prestetih_glasov": 1
    },
    {
      "st": 59,
      "naz": "KULTURNI DOM DOBRNA",
      "udel": {
        "upr": 1177,
        "gl": 671,
        "prc": 0.5701
      },
      "rez": {
        "rez": [
          {
            "st": 1,
            "gl": 0,
            "prc": null
          },
          {
            "st": 2,
            "gl": 0,
            "prc": null
          },
          {
            "st": 3,
            "gl": 0,
            "prc": null
          },
          {
            "st": 4,
            "gl": 0,
            "prc": null
          },
          {
            "st": 5,
            "gl": 0,
            "prc": null
          },
          {
            "st": 6,
            "gl": 0,
            "prc": null
          },
          {
            "st": 7,
            "gl": 0,
            "prc": null
          },
          {
            "st": 8,
            "gl": 0,
            "prc": null
          },
          {
            "st": 9,
            "gl": 0,
            "prc": null
          },
          {
            "st": 10,
            "gl": 0,
            "prc": null
          },
          {
            "st": 11,
            "gl": 0,
            "prc": null
          },
          {
            "st": 12,
            "gl": 0,
            "prc": null
          },
          {
            "st": 13,
            "gl": 0,
            "prc": null
          },
          {
            "st": 14,
            "gl": 0,
            "prc": null
          },
          {
            "st": 15,
            "gl": 0,
            "prc": null
          },
          {
            "st": 16,
            "gl": 0,
            "prc": null
          },
          {
            "st": 17,
            "gl": 0,
            "prc": null
          },
          {
            "st": 18,
            "gl": 0,
            "prc": null
          },
          {
            "st": 19,
            "gl": 0,
            "prc": null
          },
          {
            "st": 20,
            "gl": 0,
            "prc": null
          },
          {
            "st": 21,
            "gl": 0,
            "prc": null
          }
        ],
        "glas": 0,
        "velj": 0,
        "nev": 0
      },
      "prestetih_glasov": 0
    },
    {
      "st": 14,
      "naz": "KULTURNI DOM ŠKOFJA VAS, ŠKOFJA VAS 38",
      "udel": {
        "upr": 1445,
        "gl": 950,
        "prc": 0.6574
      },
      "rez": {
        "rez": [
          {
            "st": 1,
            "gl": 1,
            "prc": 0.0011
          },
          {
            "st": 2,
            "gl": 4,
            "prc": 0.0042
          },
          {
            "st": 3,
            "gl": 37,
            "prc": 0.0392
          },
          {
            "st": 4,
            "gl": 332,
            "prc": 0.3521
          },
          {
            "st": 5,
            "gl": 0,
            "prc": null
          },
          {
            "st": 6,
            "gl": 23,
            "prc": 0.0244
          },
          {
            "st": 7,
            "gl": 2,
            "prc": 0.0021
          },
          {
            "st": 8,
            "gl": 18,
            "prc": 0.0191
          },
          {
            "st": 9,
            "gl": 10,
            "prc": 0.0106
          },
          {
            "st": 10,
            "gl": 26,
            "prc": 0.0276
          },
          {
            "st": 11,
            "gl": 8,
            "prc": 0.0085
          },
          {
            "st": 12,
            "gl": 38,
            "prc": 0.0403
          },
          {
            "st": 13,
            "gl": 12,
            "prc": 0.0127
          },
          {
            "st": 14,
            "gl": 40,
            "prc": 0.0424
          },
          {
            "st": 15,
            "gl": 295,
            "prc": 0.3128
          },
          {
            "st": 16,
            "gl": 18,
            "prc": 0.0191
          },
          {
            "st": 17,
            "gl": 45,
            "prc": 0.0477
          },
          {
            "st": 18,
            "gl": 15,
            "prc": 0.0159
          },
          {
            "st": 19,
            "gl": 9,
            "prc": 0.0095
          },
          {
            "st": 20,
            "gl": 10,
            "prc": 0.0106
          },
          {
            "st": 21,
            "gl": 0,
            "prc": null
          }
        ],
        "glas": 950,
        "velj": 943,
        "nev": 7
      },
      "prestetih_glasov": 1
    },
    {
      "st": 29,
      "naz": "KULTURNI DOM ŠTORE, CESTA XIV. DIVIZIJE 29, ŠTORE",
      "udel": {
        "upr": 260,
        "gl": 171,
        "prc": 0.6577
      },
      "rez": {
        "rez": [
          {
            "st": 1,
            "gl": 2,
            "prc": 0.0119
          },
          {
            "st": 2,
            "gl": 0,
            "prc": 0
          },
          {
            "st": 3,
            "gl": 15,
            "prc": 0.0893
          },
          {
            "st": 4,
            "gl": 42,
            "prc": 0.25
          },
          {
            "st": 5,
            "gl": 0,
            "prc": null
          },
          {
            "st": 6,
            "gl": 5,
            "prc": 0.0298
          },
          {
            "st": 7,
            "gl": 1,
            "prc": 0.006
          },
          {
            "st": 8,
            "gl": 3,
            "prc": 0.0179
          },
          {
            "st": 9,
            "gl": 0,
            "prc": 0
          },
          {
            "st": 10,
            "gl": 5,
            "prc": 0.0298
          },
          {
            "st": 11,
            "gl": 0,
            "prc": 0
          },
          {
            "st": 12,
            "gl": 7,
            "prc": 0.0417
          },
          {
            "st": 13,
            "gl": 1,
            "prc": 0.006
          },
          {
            "st": 14,
            "gl": 3,
            "prc": 0.0179
          },
          {
            "st": 15,
            "gl": 68,
            "prc": 0.4048
          },
          {
            "st": 16,
            "gl": 6,
            "prc": 0.0357
          },
          {
            "st": 17,
            "gl": 6,
            "prc": 0.0357
          },
          {
            "st": 18,
            "gl": 3,
            "prc": 0.0179
          },
          {
            "st": 19,
            "gl": 0,
            "prc": 0
          },
          {
            "st": 20,
            "gl": 1,
            "prc": 0.006
          },
          {
            "st": 21,
            "gl": 0,
            "prc": null
          }
        ],
        "glas": 171,
        "velj": 168,
        "nev": 3
      },
      "prestetih_glasov": 1
    },
    {
      "st": 55,
      "naz": "MAJGER JAKOB, PRISTAVA 14B",
      "udel": {
        "upr": 542,
        "gl": 275,
        "prc": 0.5074
      },
      "rez": {
        "rez": [
          {
            "st": 1,
            "gl": 0,
            "prc": null
          },
          {
            "st": 2,
            "gl": 0,
            "prc": null
          },
          {
            "st": 3,
            "gl": 0,
            "prc": null
          },
          {
            "st": 4,
            "gl": 0,
            "prc": null
          },
          {
            "st": 5,
            "gl": 0,
            "prc": null
          },
          {
            "st": 6,
            "gl": 0,
            "prc": null
          },
          {
            "st": 7,
            "gl": 0,
            "prc": null
          },
          {
            "st": 8,
            "gl": 0,
            "prc": null
          },
          {
            "st": 9,
            "gl": 0,
            "prc": null
          },
          {
            "st": 10,
            "gl": 0,
            "prc": null
          },
          {
            "st": 11,
            "gl": 0,
            "prc": null
          },
          {
            "st": 12,
            "gl": 0,
            "prc": null
          },
          {
            "st": 13,
            "gl": 0,
            "prc": null
          },
          {
            "st": 14,
            "gl": 0,
            "prc": null
          },
          {
            "st": 15,
            "gl": 0,
            "prc": null
          },
          {
            "st": 16,
            "gl": 0,
            "prc": null
          },
          {
            "st": 17,
            "gl": 0,
            "prc": null
          },
          {
            "st": 18,
            "gl": 0,
            "prc": null
          },
          {
            "st": 19,
            "gl": 0,
            "prc": null
          },
          {
            "st": 20,
            "gl": 0,
            "prc": null
          },
          {
            "st": 21,
            "gl": 0,
            "prc": null
          }
        ],
        "glas": 0,
        "velj": 0,
        "nev": 0
      },
      "prestetih_glasov": 0
    },
    {
      "st": 35,
      "naz": "OSNOVNA ŠOLA ANTONA BEZENŠKA FRANKOLOVO (AVLA)",
      "udel": {
        "upr": 354,
        "gl": 191,
        "prc": 0.5395
      },
      "rez": {
        "rez": [
          {
            "st": 1,
            "gl": 0,
            "prc": null
          },
          {
            "st": 2,
            "gl": 0,
            "prc": null
          },
          {
            "st": 3,
            "gl": 0,
            "prc": null
          },
          {
            "st": 4,
            "gl": 0,
            "prc": null
          },
          {
            "st": 5,
            "gl": 0,
            "prc": null
          },
          {
            "st": 6,
            "gl": 0,
            "prc": null
          },
          {
            "st": 7,
            "gl": 0,
            "prc": null
          },
          {
            "st": 8,
            "gl": 0,
            "prc": null
          },
          {
            "st": 9,
            "gl": 0,
            "prc": null
          },
          {
            "st": 10,
            "gl": 0,
            "prc": null
          },
          {
            "st": 11,
            "gl": 0,
            "prc": null
          },
          {
            "st": 12,
            "gl": 0,
            "prc": null
          },
          {
            "st": 13,
            "gl": 0,
            "prc": null
          },
          {
            "st": 14,
            "gl": 0,
            "prc": null
          },
          {
            "st": 15,
            "gl": 0,
            "prc": null
          },
          {
            "st": 16,
            "gl": 0,
            "prc": null
          },
          {
            "st": 17,
            "gl": 0,
            "prc": null
          },
          {
            "st": 18,
            "gl": 0,
            "prc": null
          },
          {
            "st": 19,
            "gl": 0,
            "prc": null
          },
          {
            "st": 20,
            "gl": 0,
            "prc": null
          },
          {
            "st": 21,
            "gl": 0,
            "prc": null
          }
        ],
        "glas": 0,
        "velj": 0,
        "nev": 0
      },
      "prestetih_glasov": 0
    },
    {
      "st": 64,
      "naz": "OSNOVNA ŠOLA DOBRNA",
      "udel": {
        "upr": 132,
        "gl": 67,
        "prc": 0.5076
      },
      "rez": {
        "rez": [
          {
            "st": 1,
            "gl": 0,
            "prc": null
          },
          {
            "st": 2,
            "gl": 0,
            "prc": null
          },
          {
            "st": 3,
            "gl": 0,
            "prc": null
          },
          {
            "st": 4,
            "gl": 0,
            "prc": null
          },
          {
            "st": 5,
            "gl": 0,
            "prc": null
          },
          {
            "st": 6,
            "gl": 0,
            "prc": null
          },
          {
            "st": 7,
            "gl": 0,
            "prc": null
          },
          {
            "st": 8,
            "gl": 0,
            "prc": null
          },
          {
            "st": 9,
            "gl": 0,
            "prc": null
          },
          {
            "st": 10,
            "gl": 0,
            "prc": null
          },
          {
            "st": 11,
            "gl": 0,
            "prc": null
          },
          {
            "st": 12,
            "gl": 0,
            "prc": null
          },
          {
            "st": 13,
            "gl": 0,
            "prc": null
          },
          {
            "st": 14,
            "gl": 0,
            "prc": null
          },
          {
            "st": 15,
            "gl": 0,
            "prc": null
          },
          {
            "st": 16,
            "gl": 0,
            "prc": null
          },
          {
            "st": 17,
            "gl": 0,
            "prc": null
          },
          {
            "st": 18,
            "gl": 0,
            "prc": null
          },
          {
            "st": 19,
            "gl": 0,
            "prc": null
          },
          {
            "st": 20,
            "gl": 0,
            "prc": null
          },
          {
            "st": 21,
            "gl": 0,
            "prc": null
          }
        ],
        "glas": 0,
        "velj": 0,
        "nev": 0
      },
      "prestetih_glasov": 0
    },
    {
      "st": 1,
      "naz": "OSNOVNA ŠOLA HUDINJA",
      "udel": {
        "upr": 1279,
        "gl": 851,
        "prc": 0.6654
      },
      "rez": {
        "rez": [
          {
            "st": 1,
            "gl": 1,
            "prc": 0.0012
          },
          {
            "st": 2,
            "gl": 1,
            "prc": 0.0012
          },
          {
            "st": 3,
            "gl": 27,
            "prc": 0.0321
          },
          {
            "st": 4,
            "gl": 299,
            "prc": 0.3555
          },
          {
            "st": 5,
            "gl": 0,
            "prc": null
          },
          {
            "st": 6,
            "gl": 22,
            "prc": 0.0262
          },
          {
            "st": 7,
            "gl": 1,
            "prc": 0.0012
          },
          {
            "st": 8,
            "gl": 37,
            "prc": 0.044
          },
          {
            "st": 9,
            "gl": 12,
            "prc": 0.0143
          },
          {
            "st": 10,
            "gl": 18,
            "prc": 0.0214
          },
          {
            "st": 11,
            "gl": 10,
            "prc": 0.0119
          },
          {
            "st": 12,
            "gl": 28,
            "prc": 0.0333
          },
          {
            "st": 13,
            "gl": 18,
            "prc": 0.0214
          },
          {
            "st": 14,
            "gl": 21,
            "prc": 0.025
          },
          {
            "st": 15,
            "gl": 204,
            "prc": 0.2426
          },
          {
            "st": 16,
            "gl": 27,
            "prc": 0.0321
          },
          {
            "st": 17,
            "gl": 63,
            "prc": 0.0749
          },
          {
            "st": 18,
            "gl": 19,
            "prc": 0.0226
          },
          {
            "st": 19,
            "gl": 20,
            "prc": 0.0238
          },
          {
            "st": 20,
            "gl": 13,
            "prc": 0.0155
          },
          {
            "st": 21,
            "gl": 0,
            "prc": null
          }
        ],
        "glas": 851,
        "velj": 841,
        "nev": 10
      },
      "prestetih_glasov": 1
    },
    {
      "st": 25,
      "naz": "OSNOVNA ŠOLA KOMPOLE, KOMPOLE 92,ŠTORE",
      "udel": {
        "upr": 542,
        "gl": 378,
        "prc": 0.6974
      },
      "rez": {
        "rez": [
          {
            "st": 1,
            "gl": 1,
            "prc": 0.0027
          },
          {
            "st": 2,
            "gl": 1,
            "prc": 0.0027
          },
          {
            "st": 3,
            "gl": 11,
            "prc": 0.0298
          },
          {
            "st": 4,
            "gl": 122,
            "prc": 0.3306
          },
          {
            "st": 5,
            "gl": 0,
            "prc": null
          },
          {
            "st": 6,
            "gl": 11,
            "prc": 0.0298
          },
          {
            "st": 7,
            "gl": 1,
            "prc": 0.0027
          },
          {
            "st": 8,
            "gl": 13,
            "prc": 0.0352
          },
          {
            "st": 9,
            "gl": 7,
            "prc": 0.019
          },
          {
            "st": 10,
            "gl": 2,
            "prc": 0.0054
          },
          {
            "st": 11,
            "gl": 3,
            "prc": 0.0081
          },
          {
            "st": 12,
            "gl": 26,
            "prc": 0.0705
          },
          {
            "st": 13,
            "gl": 9,
            "prc": 0.0244
          },
          {
            "st": 14,
            "gl": 10,
            "prc": 0.0271
          },
          {
            "st": 15,
            "gl": 100,
            "prc": 0.271
          },
          {
            "st": 16,
            "gl": 8,
            "prc": 0.0217
          },
          {
            "st": 17,
            "gl": 20,
            "prc": 0.0542
          },
          {
            "st": 18,
            "gl": 5,
            "prc": 0.0136
          },
          {
            "st": 19,
            "gl": 7,
            "prc": 0.019
          },
          {
            "st": 20,
            "gl": 12,
            "prc": 0.0325
          },
          {
            "st": 21,
            "gl": 0,
            "prc": null
          }
        ],
        "glas": 378,
        "velj": 369,
        "nev": 9
      },
      "prestetih_glasov": 1
    },
    {
      "st": 7,
      "naz": "OSNOVNA ŠOLA LAVA",
      "udel": {
        "upr": 1163,
        "gl": 762,
        "prc": 0.6552
      },
      "rez": {
        "rez": [
          {
            "st": 1,
            "gl": 5,
            "prc": 0.0066
          },
          {
            "st": 2,
            "gl": 2,
            "prc": 0.0026
          },
          {
            "st": 3,
            "gl": 28,
            "prc": 0.037
          },
          {
            "st": 4,
            "gl": 292,
            "prc": 0.3862
          },
          {
            "st": 5,
            "gl": 0,
            "prc": null
          },
          {
            "st": 6,
            "gl": 32,
            "prc": 0.0423
          },
          {
            "st": 7,
            "gl": 1,
            "prc": 0.0013
          },
          {
            "st": 8,
            "gl": 17,
            "prc": 0.0225
          },
          {
            "st": 9,
            "gl": 5,
            "prc": 0.0066
          },
          {
            "st": 10,
            "gl": 26,
            "prc": 0.0344
          },
          {
            "st": 11,
            "gl": 9,
            "prc": 0.0119
          },
          {
            "st": 12,
            "gl": 28,
            "prc": 0.037
          },
          {
            "st": 13,
            "gl": 17,
            "prc": 0.0225
          },
          {
            "st": 14,
            "gl": 26,
            "prc": 0.0344
          },
          {
            "st": 15,
            "gl": 153,
            "prc": 0.2024
          },
          {
            "st": 16,
            "gl": 13,
            "prc": 0.0172
          },
          {
            "st": 17,
            "gl": 61,
            "prc": 0.0807
          },
          {
            "st": 18,
            "gl": 23,
            "prc": 0.0304
          },
          {
            "st": 19,
            "gl": 13,
            "prc": 0.0172
          },
          {
            "st": 20,
            "gl": 5,
            "prc": 0.0066
          },
          {
            "st": 21,
            "gl": 0,
            "prc": null
          }
        ],
        "glas": 762,
        "velj": 756,
        "nev": 6
      },
      "prestetih_glasov": 1
    },
    {
      "st": 45,
      "naz": "OSNOVNA ŠOLA SOCKA, SOCKA 70",
      "udel": {
        "upr": 584,
        "gl": 325,
        "prc": 0.5565
      },
      "rez": {
        "rez": [
          {
            "st": 1,
            "gl": 0,
            "prc": null
          },
          {
            "st": 2,
            "gl": 0,
            "prc": null
          },
          {
            "st": 3,
            "gl": 0,
            "prc": null
          },
          {
            "st": 4,
            "gl": 0,
            "prc": null
          },
          {
            "st": 5,
            "gl": 0,
            "prc": null
          },
          {
            "st": 6,
            "gl": 0,
            "prc": null
          },
          {
            "st": 7,
            "gl": 0,
            "prc": null
          },
          {
            "st": 8,
            "gl": 0,
            "prc": null
          },
          {
            "st": 9,
            "gl": 0,
            "prc": null
          },
          {
            "st": 10,
            "gl": 0,
            "prc": null
          },
          {
            "st": 11,
            "gl": 0,
            "prc": null
          },
          {
            "st": 12,
            "gl": 0,
            "prc": null
          },
          {
            "st": 13,
            "gl": 0,
            "prc": null
          },
          {
            "st": 14,
            "gl": 0,
            "prc": null
          },
          {
            "st": 15,
            "gl": 0,
            "prc": null
          },
          {
            "st": 16,
            "gl": 0,
            "prc": null
          },
          {
            "st": 17,
            "gl": 0,
            "prc": null
          },
          {
            "st": 18,
            "gl": 0,
            "prc": null
          },
          {
            "st": 19,
            "gl": 0,
            "prc": null
          },
          {
            "st": 20,
            "gl": 0,
            "prc": null
          },
          {
            "st": 21,
            "gl": 0,
            "prc": null
          }
        ],
        "glas": 0,
        "velj": 0,
        "nev": 0
      },
      "prestetih_glasov": 0
    },
    {
      "st": 31,
      "naz": "OSNOVNA ŠOLA ŠTORE",
      "udel": {
        "upr": 1026,
        "gl": 561,
        "prc": 0.5468
      },
      "rez": {
        "rez": [
          {
            "st": 1,
            "gl": 0,
            "prc": null
          },
          {
            "st": 2,
            "gl": 0,
            "prc": null
          },
          {
            "st": 3,
            "gl": 0,
            "prc": null
          },
          {
            "st": 4,
            "gl": 0,
            "prc": null
          },
          {
            "st": 5,
            "gl": 0,
            "prc": null
          },
          {
            "st": 6,
            "gl": 0,
            "prc": null
          },
          {
            "st": 7,
            "gl": 0,
            "prc": null
          },
          {
            "st": 8,
            "gl": 0,
            "prc": null
          },
          {
            "st": 9,
            "gl": 0,
            "prc": null
          },
          {
            "st": 10,
            "gl": 0,
            "prc": null
          },
          {
            "st": 11,
            "gl": 0,
            "prc": null
          },
          {
            "st": 12,
            "gl": 0,
            "prc": null
          },
          {
            "st": 13,
            "gl": 0,
            "prc": null
          },
          {
            "st": 14,
            "gl": 0,
            "prc": null
          },
          {
            "st": 15,
            "gl": 0,
            "prc": null
          },
          {
            "st": 16,
            "gl": 0,
            "prc": null
          },
          {
            "st": 17,
            "gl": 0,
            "prc": null
          },
          {
            "st": 18,
            "gl": 0,
            "prc": null
          },
          {
            "st": 19,
            "gl": 0,
            "prc": null
          },
          {
            "st": 20,
            "gl": 0,
            "prc": null
          },
          {
            "st": 21,
            "gl": 0,
            "prc": null
          }
        ],
        "glas": 0,
        "velj": 0,
        "nev": 0
      },
      "prestetih_glasov": 0
    },
    {
      "st": 51,
      "naz": "OSNOVNA ŠOLA VOJNIK",
      "udel": {
        "upr": 1134,
        "gl": 584,
        "prc": 0.515
      },
      "rez": {
        "rez": [
          {
            "st": 1,
            "gl": 0,
            "prc": null
          },
          {
            "st": 2,
            "gl": 0,
            "prc": null
          },
          {
            "st": 3,
            "gl": 0,
            "prc": null
          },
          {
            "st": 4,
            "gl": 0,
            "prc": null
          },
          {
            "st": 5,
            "gl": 0,
            "prc": null
          },
          {
            "st": 6,
            "gl": 0,
            "prc": null
          },
          {
            "st": 7,
            "gl": 0,
            "prc": null
          },
          {
            "st": 8,
            "gl": 0,
            "prc": null
          },
          {
            "st": 9,
            "gl": 0,
            "prc": null
          },
          {
            "st": 10,
            "gl": 0,
            "prc": null
          },
          {
            "st": 11,
            "gl": 0,
            "prc": null
          },
          {
            "st": 12,
            "gl": 0,
            "prc": null
          },
          {
            "st": 13,
            "gl": 0,
            "prc": null
          },
          {
            "st": 14,
            "gl": 0,
            "prc": null
          },
          {
            "st": 15,
            "gl": 0,
            "prc": null
          },
          {
            "st": 16,
            "gl": 0,
            "prc": null
          },
          {
            "st": 17,
            "gl": 0,
            "prc": null
          },
          {
            "st": 18,
            "gl": 0,
            "prc": null
          },
          {
            "st": 19,
            "gl": 0,
            "prc": null
          },
          {
            "st": 20,
            "gl": 0,
            "prc": null
          },
          {
            "st": 21,
            "gl": 0,
            "prc": null
          }
        ],
        "glas": 0,
        "velj": 0,
        "nev": 0
      },
      "prestetih_glasov": 0
    },
    {
      "st": 52,
      "naz": "OSNOVNA ŠOLA VOJNIK",
      "udel": {
        "upr": 906,
        "gl": 643,
        "prc": 0.7097
      },
      "rez": {
        "rez": [
          {
            "st": 1,
            "gl": 4,
            "prc": 0.0063
          },
          {
            "st": 2,
            "gl": 0,
            "prc": 0
          },
          {
            "st": 3,
            "gl": 13,
            "prc": 0.0204
          },
          {
            "st": 4,
            "gl": 227,
            "prc": 0.3564
          },
          {
            "st": 5,
            "gl": 0,
            "prc": null
          },
          {
            "st": 6,
            "gl": 15,
            "prc": 0.0235
          },
          {
            "st": 7,
            "gl": 6,
            "prc": 0.0094
          },
          {
            "st": 8,
            "gl": 9,
            "prc": 0.0141
          },
          {
            "st": 9,
            "gl": 9,
            "prc": 0.0141
          },
          {
            "st": 10,
            "gl": 16,
            "prc": 0.0251
          },
          {
            "st": 11,
            "gl": 9,
            "prc": 0.0141
          },
          {
            "st": 12,
            "gl": 40,
            "prc": 0.0628
          },
          {
            "st": 13,
            "gl": 11,
            "prc": 0.0173
          },
          {
            "st": 14,
            "gl": 28,
            "prc": 0.044
          },
          {
            "st": 15,
            "gl": 171,
            "prc": 0.2684
          },
          {
            "st": 16,
            "gl": 10,
            "prc": 0.0157
          },
          {
            "st": 17,
            "gl": 32,
            "prc": 0.0502
          },
          {
            "st": 18,
            "gl": 21,
            "prc": 0.033
          },
          {
            "st": 19,
            "gl": 10,
            "prc": 0.0157
          },
          {
            "st": 20,
            "gl": 6,
            "prc": 0.0094
          },
          {
            "st": 21,
            "gl": 0,
            "prc": null
          }
        ],
        "glas": 643,
        "velj": 637,
        "nev": 6
      },
      "prestetih_glasov": 1
    },
    {
      "st": 53,
      "naz": "OSTRI, RAVNAK IVAN, CELJSKA CESTA 2B",
      "udel": {
        "upr": 455,
        "gl": 255,
        "prc": 0.5604
      },
      "rez": {
        "rez": [
          {
            "st": 1,
            "gl": 0,
            "prc": null
          },
          {
            "st": 2,
            "gl": 0,
            "prc": null
          },
          {
            "st": 3,
            "gl": 0,
            "prc": null
          },
          {
            "st": 4,
            "gl": 0,
            "prc": null
          },
          {
            "st": 5,
            "gl": 0,
            "prc": null
          },
          {
            "st": 6,
            "gl": 0,
            "prc": null
          },
          {
            "st": 7,
            "gl": 0,
            "prc": null
          },
          {
            "st": 8,
            "gl": 0,
            "prc": null
          },
          {
            "st": 9,
            "gl": 0,
            "prc": null
          },
          {
            "st": 10,
            "gl": 0,
            "prc": null
          },
          {
            "st": 11,
            "gl": 0,
            "prc": null
          },
          {
            "st": 12,
            "gl": 0,
            "prc": null
          },
          {
            "st": 13,
            "gl": 0,
            "prc": null
          },
          {
            "st": 14,
            "gl": 0,
            "prc": null
          },
          {
            "st": 15,
            "gl": 0,
            "prc": null
          },
          {
            "st": 16,
            "gl": 0,
            "prc": null
          },
          {
            "st": 17,
            "gl": 0,
            "prc": null
          },
          {
            "st": 18,
            "gl": 0,
            "prc": null
          },
          {
            "st": 19,
            "gl": 0,
            "prc": null
          },
          {
            "st": 20,
            "gl": 0,
            "prc": null
          },
          {
            "st": 21,
            "gl": 0,
            "prc": null
          }
        ],
        "glas": 0,
        "velj": 0,
        "nev": 0
      },
      "prestetih_glasov": 0
    },
    {
      "st": 5,
      "naz": "OSTROŽNIK - HORVAT KARINA, BUKOVŽLAK 51 A",
      "udel": {
        "upr": 280,
        "gl": 191,
        "prc": 0.6821
      },
      "rez": {
        "rez": [
          {
            "st": 1,
            "gl": 1,
            "prc": 0.0053
          },
          {
            "st": 2,
            "gl": 1,
            "prc": 0.0053
          },
          {
            "st": 3,
            "gl": 12,
            "prc": 0.0635
          },
          {
            "st": 4,
            "gl": 55,
            "prc": 0.291
          },
          {
            "st": 5,
            "gl": 0,
            "prc": null
          },
          {
            "st": 6,
            "gl": 3,
            "prc": 0.0159
          },
          {
            "st": 7,
            "gl": 1,
            "prc": 0.0053
          },
          {
            "st": 8,
            "gl": 7,
            "prc": 0.037
          },
          {
            "st": 9,
            "gl": 4,
            "prc": 0.0212
          },
          {
            "st": 10,
            "gl": 6,
            "prc": 0.0317
          },
          {
            "st": 11,
            "gl": 3,
            "prc": 0.0159
          },
          {
            "st": 12,
            "gl": 13,
            "prc": 0.0688
          },
          {
            "st": 13,
            "gl": 2,
            "prc": 0.0106
          },
          {
            "st": 14,
            "gl": 6,
            "prc": 0.0317
          },
          {
            "st": 15,
            "gl": 50,
            "prc": 0.2646
          },
          {
            "st": 16,
            "gl": 6,
            "prc": 0.0317
          },
          {
            "st": 17,
            "gl": 10,
            "prc": 0.0529
          },
          {
            "st": 18,
            "gl": 5,
            "prc": 0.0265
          },
          {
            "st": 19,
            "gl": 4,
            "prc": 0.0212
          },
          {
            "st": 20,
            "gl": 0,
            "prc": 0
          },
          {
            "st": 21,
            "gl": 0,
            "prc": null
          }
        ],
        "glas": 191,
        "velj": 189,
        "nev": 2
      },
      "prestetih_glasov": 1
    },
    {
      "st": 3,
      "naz": "SEDEŽ MČ HUDINJA",
      "udel": {
        "upr": 793,
        "gl": 512,
        "prc": 0.6456
      },
      "rez": {
        "rez": [
          {
            "st": 1,
            "gl": 2,
            "prc": 0.0039
          },
          {
            "st": 2,
            "gl": 1,
            "prc": 0.002
          },
          {
            "st": 3,
            "gl": 13,
            "prc": 0.0256
          },
          {
            "st": 4,
            "gl": 192,
            "prc": 0.378
          },
          {
            "st": 5,
            "gl": 0,
            "prc": null
          },
          {
            "st": 6,
            "gl": 25,
            "prc": 0.0492
          },
          {
            "st": 7,
            "gl": 3,
            "prc": 0.0059
          },
          {
            "st": 8,
            "gl": 26,
            "prc": 0.0512
          },
          {
            "st": 9,
            "gl": 1,
            "prc": 0.002
          },
          {
            "st": 10,
            "gl": 15,
            "prc": 0.0295
          },
          {
            "st": 11,
            "gl": 15,
            "prc": 0.0295
          },
          {
            "st": 12,
            "gl": 21,
            "prc": 0.0413
          },
          {
            "st": 13,
            "gl": 13,
            "prc": 0.0256
          },
          {
            "st": 14,
            "gl": 22,
            "prc": 0.0433
          },
          {
            "st": 15,
            "gl": 95,
            "prc": 0.187
          },
          {
            "st": 16,
            "gl": 9,
            "prc": 0.0177
          },
          {
            "st": 17,
            "gl": 25,
            "prc": 0.0492
          },
          {
            "st": 18,
            "gl": 18,
            "prc": 0.0354
          },
          {
            "st": 19,
            "gl": 9,
            "prc": 0.0177
          },
          {
            "st": 20,
            "gl": 3,
            "prc": 0.0059
          },
          {
            "st": 21,
            "gl": 0,
            "prc": null
          }
        ],
        "glas": 512,
        "velj": 508,
        "nev": 4
      },
      "prestetih_glasov": 1
    },
    {
      "st": 8,
      "naz": "SEDEŽ MČ LAVA",
      "udel": {
        "upr": 923,
        "gl": 582,
        "prc": 0.6306
      },
      "rez": {
        "rez": [
          {
            "st": 1,
            "gl": 4,
            "prc": 0.007
          },
          {
            "st": 2,
            "gl": 0,
            "prc": 0
          },
          {
            "st": 3,
            "gl": 34,
            "prc": 0.0596
          },
          {
            "st": 4,
            "gl": 189,
            "prc": 0.3316
          },
          {
            "st": 5,
            "gl": 0,
            "prc": null
          },
          {
            "st": 6,
            "gl": 28,
            "prc": 0.0491
          },
          {
            "st": 7,
            "gl": 6,
            "prc": 0.0105
          },
          {
            "st": 8,
            "gl": 16,
            "prc": 0.0281
          },
          {
            "st": 9,
            "gl": 4,
            "prc": 0.007
          },
          {
            "st": 10,
            "gl": 15,
            "prc": 0.0263
          },
          {
            "st": 11,
            "gl": 4,
            "prc": 0.007
          },
          {
            "st": 12,
            "gl": 27,
            "prc": 0.0474
          },
          {
            "st": 13,
            "gl": 7,
            "prc": 0.0123
          },
          {
            "st": 14,
            "gl": 18,
            "prc": 0.0316
          },
          {
            "st": 15,
            "gl": 145,
            "prc": 0.2544
          },
          {
            "st": 16,
            "gl": 11,
            "prc": 0.0193
          },
          {
            "st": 17,
            "gl": 26,
            "prc": 0.0456
          },
          {
            "st": 18,
            "gl": 18,
            "prc": 0.0316
          },
          {
            "st": 19,
            "gl": 3,
            "prc": 0.0053
          },
          {
            "st": 20,
            "gl": 15,
            "prc": 0.0263
          },
          {
            "st": 21,
            "gl": 0,
            "prc": null
          }
        ],
        "glas": 582,
        "velj": 570,
        "nev": 12
      },
      "prestetih_glasov": 1
    },
    {
      "st": 21,
      "naz": "ŠPORTNO DRUŠTVO ZAČRET",
      "udel": {
        "upr": 298,
        "gl": 227,
        "prc": 0.7617
      },
      "rez": {
        "rez": [
          {
            "st": 1,
            "gl": 5,
            "prc": 0.022
          },
          {
            "st": 2,
            "gl": 0,
            "prc": 0
          },
          {
            "st": 3,
            "gl": 11,
            "prc": 0.0485
          },
          {
            "st": 4,
            "gl": 78,
            "prc": 0.3436
          },
          {
            "st": 5,
            "gl": 0,
            "prc": null
          },
          {
            "st": 6,
            "gl": 3,
            "prc": 0.0132
          },
          {
            "st": 7,
            "gl": 0,
            "prc": 0
          },
          {
            "st": 8,
            "gl": 3,
            "prc": 0.0132
          },
          {
            "st": 9,
            "gl": 4,
            "prc": 0.0176
          },
          {
            "st": 10,
            "gl": 2,
            "prc": 0.0088
          },
          {
            "st": 11,
            "gl": 0,
            "prc": 0
          },
          {
            "st": 12,
            "gl": 16,
            "prc": 0.0705
          },
          {
            "st": 13,
            "gl": 2,
            "prc": 0.0088
          },
          {
            "st": 14,
            "gl": 8,
            "prc": 0.0352
          },
          {
            "st": 15,
            "gl": 74,
            "prc": 0.326
          },
          {
            "st": 16,
            "gl": 2,
            "prc": 0.0088
          },
          {
            "st": 17,
            "gl": 13,
            "prc": 0.0573
          },
          {
            "st": 18,
            "gl": 3,
            "prc": 0.0132
          },
          {
            "st": 19,
            "gl": 3,
            "prc": 0.0132
          },
          {
            "st": 20,
            "gl": 0,
            "prc": 0
          },
          {
            "st": 21,
            "gl": 0,
            "prc": null
          }
        ],
        "glas": 227,
        "velj": 227,
        "nev": 0
      },
      "prestetih_glasov": 1
    },
    {
      "st": 26,
      "naz": "ŠUHEL PAVEL, LAŠKA VAS 41, ŠTORE",
      "udel": {
        "upr": 186,
        "gl": 137,
        "prc": 0.7366
      },
      "rez": {
        "rez": [
          {
            "st": 1,
            "gl": 0,
            "prc": 0
          },
          {
            "st": 2,
            "gl": 0,
            "prc": 0
          },
          {
            "st": 3,
            "gl": 7,
            "prc": 0.0511
          },
          {
            "st": 4,
            "gl": 49,
            "prc": 0.3577
          },
          {
            "st": 5,
            "gl": 0,
            "prc": null
          },
          {
            "st": 6,
            "gl": 8,
            "prc": 0.0584
          },
          {
            "st": 7,
            "gl": 1,
            "prc": 0.0073
          },
          {
            "st": 8,
            "gl": 6,
            "prc": 0.0438
          },
          {
            "st": 9,
            "gl": 1,
            "prc": 0.0073
          },
          {
            "st": 10,
            "gl": 1,
            "prc": 0.0073
          },
          {
            "st": 11,
            "gl": 5,
            "prc": 0.0365
          },
          {
            "st": 12,
            "gl": 9,
            "prc": 0.0657
          },
          {
            "st": 13,
            "gl": 1,
            "prc": 0.0073
          },
          {
            "st": 14,
            "gl": 4,
            "prc": 0.0292
          },
          {
            "st": 15,
            "gl": 28,
            "prc": 0.2044
          },
          {
            "st": 16,
            "gl": 7,
            "prc": 0.0511
          },
          {
            "st": 17,
            "gl": 7,
            "prc": 0.0511
          },
          {
            "st": 18,
            "gl": 1,
            "prc": 0.0073
          },
          {
            "st": 19,
            "gl": 1,
            "prc": 0.0073
          },
          {
            "st": 20,
            "gl": 1,
            "prc": 0.0073
          },
          {
            "st": 21,
            "gl": 0,
            "prc": null
          }
        ],
        "glas": 137,
        "velj": 137,
        "nev": 0
      },
      "prestetih_glasov": 1
    },
    {
      "st": 44,
      "naz": "VEČNAMENSKA DVORANA POŠ NOVA CERKEV,NOVA CERKEV41",
      "udel": {
        "upr": 1137,
        "gl": 778,
        "prc": 0.6843
      },
      "rez": {
        "rez": [
          {
            "st": 1,
            "gl": 4,
            "prc": 0.0052
          },
          {
            "st": 2,
            "gl": 0,
            "prc": 0
          },
          {
            "st": 3,
            "gl": 17,
            "prc": 0.022
          },
          {
            "st": 4,
            "gl": 184,
            "prc": 0.2387
          },
          {
            "st": 5,
            "gl": 0,
            "prc": null
          },
          {
            "st": 6,
            "gl": 11,
            "prc": 0.0143
          },
          {
            "st": 7,
            "gl": 2,
            "prc": 0.0026
          },
          {
            "st": 8,
            "gl": 37,
            "prc": 0.048
          },
          {
            "st": 9,
            "gl": 8,
            "prc": 0.0104
          },
          {
            "st": 10,
            "gl": 16,
            "prc": 0.0208
          },
          {
            "st": 11,
            "gl": 13,
            "prc": 0.0169
          },
          {
            "st": 12,
            "gl": 71,
            "prc": 0.0921
          },
          {
            "st": 13,
            "gl": 13,
            "prc": 0.0169
          },
          {
            "st": 14,
            "gl": 41,
            "prc": 0.0532
          },
          {
            "st": 15,
            "gl": 286,
            "prc": 0.3709
          },
          {
            "st": 16,
            "gl": 17,
            "prc": 0.022
          },
          {
            "st": 17,
            "gl": 21,
            "prc": 0.0272
          },
          {
            "st": 18,
            "gl": 19,
            "prc": 0.0246
          },
          {
            "st": 19,
            "gl": 9,
            "prc": 0.0117
          },
          {
            "st": 20,
            "gl": 2,
            "prc": 0.0026
          },
          {
            "st": 21,
            "gl": 0,
            "prc": null
          }
        ],
        "glas": 778,
        "velj": 771,
        "nev": 7
      },
      "prestetih_glasov": 1
    },
    {
      "st": 54,
      "naz": "VRBIČ FRANC, MALE DOLE 44",
      "udel": {
        "upr": 405,
        "gl": 281,
        "prc": 0.6938
      },
      "rez": {
        "rez": [
          {
            "st": 1,
            "gl": 2,
            "prc": 0.0072
          },
          {
            "st": 2,
            "gl": 0,
            "prc": 0
          },
          {
            "st": 3,
            "gl": 5,
            "prc": 0.0181
          },
          {
            "st": 4,
            "gl": 50,
            "prc": 0.1812
          },
          {
            "st": 5,
            "gl": 0,
            "prc": null
          },
          {
            "st": 6,
            "gl": 4,
            "prc": 0.0145
          },
          {
            "st": 7,
            "gl": 1,
            "prc": 0.0036
          },
          {
            "st": 8,
            "gl": 6,
            "prc": 0.0217
          },
          {
            "st": 9,
            "gl": 7,
            "prc": 0.0254
          },
          {
            "st": 10,
            "gl": 2,
            "prc": 0.0072
          },
          {
            "st": 11,
            "gl": 0,
            "prc": 0
          },
          {
            "st": 12,
            "gl": 26,
            "prc": 0.0942
          },
          {
            "st": 13,
            "gl": 3,
            "prc": 0.0109
          },
          {
            "st": 14,
            "gl": 6,
            "prc": 0.0217
          },
          {
            "st": 15,
            "gl": 141,
            "prc": 0.5109
          },
          {
            "st": 16,
            "gl": 4,
            "prc": 0.0145
          },
          {
            "st": 17,
            "gl": 10,
            "prc": 0.0362
          },
          {
            "st": 18,
            "gl": 5,
            "prc": 0.0181
          },
          {
            "st": 19,
            "gl": 1,
            "prc": 0.0036
          },
          {
            "st": 20,
            "gl": 3,
            "prc": 0.0109
          },
          {
            "st": 21,
            "gl": 0,
            "prc": null
          }
        ],
        "glas": 281,
        "velj": 276,
        "nev": 5
      },
      "prestetih_glasov": 1
    },
    {
      "st": 58,
      "naz": "ZDRAVSTVENI DOM DOBRNA",
      "udel": {
        "upr": 438,
        "gl": 295,
        "prc": 0.6735
      },
      "rez": {
        "rez": [
          {
            "st": 1,
            "gl": 5,
            "prc": 0.0171
          },
          {
            "st": 2,
            "gl": 0,
            "prc": 0
          },
          {
            "st": 3,
            "gl": 7,
            "prc": 0.024
          },
          {
            "st": 4,
            "gl": 110,
            "prc": 0.3767
          },
          {
            "st": 5,
            "gl": 0,
            "prc": null
          },
          {
            "st": 6,
            "gl": 6,
            "prc": 0.0205
          },
          {
            "st": 7,
            "gl": 0,
            "prc": 0
          },
          {
            "st": 8,
            "gl": 7,
            "prc": 0.024
          },
          {
            "st": 9,
            "gl": 1,
            "prc": 0.0034
          },
          {
            "st": 10,
            "gl": 5,
            "prc": 0.0171
          },
          {
            "st": 11,
            "gl": 8,
            "prc": 0.0274
          },
          {
            "st": 12,
            "gl": 25,
            "prc": 0.0856
          },
          {
            "st": 13,
            "gl": 4,
            "prc": 0.0137
          },
          {
            "st": 14,
            "gl": 16,
            "prc": 0.0548
          },
          {
            "st": 15,
            "gl": 62,
            "prc": 0.2123
          },
          {
            "st": 16,
            "gl": 7,
            "prc": 0.024
          },
          {
            "st": 17,
            "gl": 14,
            "prc": 0.0479
          },
          {
            "st": 18,
            "gl": 7,
            "prc": 0.024
          },
          {
            "st": 19,
            "gl": 4,
            "prc": 0.0137
          },
          {
            "st": 20,
            "gl": 4,
            "prc": 0.0137
          },
          {
            "st": 21,
            "gl": 0,
            "prc": null
          }
        ],
        "glas": 295,
        "velj": 292,
        "nev": 3
      },
      "prestetih_glasov": 1
    },
    {
      "st": 27,
      "naz": "ZLATKO CMOK, PEČOVJE 4A, ŠTORE",
      "udel": {
        "upr": 222,
        "gl": 166,
        "prc": 0.7477
      },
      "rez": {
        "rez": [
          {
            "st": 1,
            "gl": 1,
            "prc": 0.0061
          },
          {
            "st": 2,
            "gl": 0,
            "prc": 0
          },
          {
            "st": 3,
            "gl": 5,
            "prc": 0.0305
          },
          {
            "st": 4,
            "gl": 56,
            "prc": 0.3415
          },
          {
            "st": 5,
            "gl": 0,
            "prc": null
          },
          {
            "st": 6,
            "gl": 3,
            "prc": 0.0183
          },
          {
            "st": 7,
            "gl": 0,
            "prc": 0
          },
          {
            "st": 8,
            "gl": 8,
            "prc": 0.0488
          },
          {
            "st": 9,
            "gl": 1,
            "prc": 0.0061
          },
          {
            "st": 10,
            "gl": 0,
            "prc": 0
          },
          {
            "st": 11,
            "gl": 1,
            "prc": 0.0061
          },
          {
            "st": 12,
            "gl": 13,
            "prc": 0.0793
          },
          {
            "st": 13,
            "gl": 3,
            "prc": 0.0183
          },
          {
            "st": 14,
            "gl": 4,
            "prc": 0.0244
          },
          {
            "st": 15,
            "gl": 54,
            "prc": 0.3293
          },
          {
            "st": 16,
            "gl": 2,
            "prc": 0.0122
          },
          {
            "st": 17,
            "gl": 8,
            "prc": 0.0488
          },
          {
            "st": 18,
            "gl": 3,
            "prc": 0.0183
          },
          {
            "st": 19,
            "gl": 2,
            "prc": 0.0122
          },
          {
            "st": 20,
            "gl": 0,
            "prc": 0
          },
          {
            "st": 21,
            "gl": 0,
            "prc": null
          }
        ],
        "glas": 166,
        "velj": 164,
        "nev": 2
      },
      "prestetih_glasov": 1
    },
    {
      "st": 901,
      "naz": "PREDČASNO GLASOVANJE",
      "udel": {
        "upr": null,
        "gl": 1745,
        "prc": null
      },
      "rez": {
        "rez": [
          {
            "st": 1,
            "gl": 13,
            "prc": 0.0075
          },
          {
            "st": 2,
            "gl": 4,
            "prc": 0.0023
          },
          {
            "st": 3,
            "gl": 30,
            "prc": 0.0174
          },
          {
            "st": 4,
            "gl": 696,
            "prc": 0.4025
          },
          {
            "st": 5,
            "gl": 0,
            "prc": null
          },
          {
            "st": 6,
            "gl": 80,
            "prc": 0.0463
          },
          {
            "st": 7,
            "gl": 1,
            "prc": 0.0006
          },
          {
            "st": 8,
            "gl": 48,
            "prc": 0.0278
          },
          {
            "st": 9,
            "gl": 16,
            "prc": 0.0093
          },
          {
            "st": 10,
            "gl": 44,
            "prc": 0.0254
          },
          {
            "st": 11,
            "gl": 25,
            "prc": 0.0145
          },
          {
            "st": 12,
            "gl": 73,
            "prc": 0.0422
          },
          {
            "st": 13,
            "gl": 13,
            "prc": 0.0075
          },
          {
            "st": 14,
            "gl": 88,
            "prc": 0.0509
          },
          {
            "st": 15,
            "gl": 373,
            "prc": 0.2157
          },
          {
            "st": 16,
            "gl": 22,
            "prc": 0.0127
          },
          {
            "st": 17,
            "gl": 129,
            "prc": 0.0746
          },
          {
            "st": 18,
            "gl": 25,
            "prc": 0.0145
          },
          {
            "st": 19,
            "gl": 40,
            "prc": 0.0231
          },
          {
            "st": 20,
            "gl": 9,
            "prc": 0.0052
          },
          {
            "st": 21,
            "gl": 0,
            "prc": null
          }
        ],
        "glas": 1745,
        "velj": 1729,
        "nev": 16
      },
      "prestetih_glasov": 1
    }
  ],
  "liste": [
    {
      "ime": "Vili",
      "pri": "Šmid",
      "st": 1,
      "naz": "DeSUS - DEMOKRATIČNA STRANKA UPOKOJENCEV SLOVENIJE",
      "knaz": "DeSUS",
      "hcol": "8DBC15"
    },
    {
      "ime": "Uroš",
      "pri": "Palhartinger",
      "st": 2,
      "naz": "DOMOVINSKA LIGA - DOM",
      "knaz": "DOM",
      "hcol": "023463"
    },
    {
      "ime": "Mateja",
      "pri": "Pozeb",
      "st": 3,
      "naz": "Državljansko gibanje Resni.ca",
      "knaz": "Resni.ca",
      "hcol": "67359A"
    },
    {
      "ime": "Miha",
      "pri": "Lamut",
      "man": true,
      "st": 4,
      "naz": "GIBANJE SVOBODA",
      "knaz": "SVOBODA",
      "hcol": "005DA3"
    },
    {
      "st": 5,
      "naz": "Gibanje Zedinjena Slovenija - ZSi",
      "knaz": "ZSi",
      "hcol": "C6EFFA"
    },
    {
      "ime": "Žiga",
      "pri": "Vipotnik",
      "st": 6,
      "naz": "LEVICA",
      "knaz": "LEVICA",
      "hcol": "FB4C48"
    },
    {
      "ime": "Radomir",
      "pri": "Kopranović",
      "st": 7,
      "naz": "Lista Borisa Popoviča - Digitalizirajmo Slovenijo",
      "knaz": "L'BP",
      "hcol": "0089CD"
    },
    {
      "ime": "Dušan",
      "pri": "Leban",
      "st": 8,
      "naz": "LISTA MARJANA ŠARCA - LMŠ",
      "knaz": "LMŠ",
      "hcol": "23A567"
    },
    {
      "ime": "Rok",
      "pri": "Kopitar",
      "st": 9,
      "naz": "NAŠA DEŽELA stranka dr. ALEKSANDRE PIVEC",
      "knaz": "NAŠA DEŽELA",
      "hcol": "126C00"
    },
    {
      "ime": "Sandi",
      "pri": "Sendelbah",
      "st": 10,
      "naz": "NAŠA PRIHODNOST IN DOBRA DRŽAVA",
      "knaz": "SNP-DD",
      "hcol": "8DE0FD"
    },
    {
      "ime": "Mateja",
      "pri": "Kreuh",
      "st": 11,
      "naz": "NESTRANKARSKA LJUDSKA LISTA GIBANJA ZDRAVA DRUŽBA",
      "knaz": "NESTRANKARSKA",
      "hcol": "ADA702"
    },
    {
      "ime": "Primož",
      "pri": "Slakan",
      "st": 12,
      "naz": "NOVA SLOVENIJA - KRŠČANSKI DEMOKRATI",
      "knaz": "NSi",
      "hcol": "009AC7"
    },
    {
      "ime": "Maja",
      "pri": "Šaver",
      "st": 13,
      "naz": "PIRATSKA STRANKA SLOVENIJE",
      "knaz": "Pirati",
      "hcol": "000000"
    },
    {
      "ime": "Roman",
      "pri": "Pungartnik",
      "st": 14,
      "naz": "POVEŽIMO SLOVENIJO (KONKRETNO, ZELENI, SLS, NLS, NS)",
      "knaz": "POVEŽIMO",
      "hcol": "E8AB02"
    },
    {
      "ime": "Damjan",
      "pri": "Muzel",
      "st": 15,
      "naz": "SLOVENSKA DEMOKRATSKA STRANKA - SDS",
      "knaz": "SDS",
      "hcol": "FFE53F"
    },
    {
      "ime": "Konrad",
      "pri": "Križanec",
      "st": 16,
      "naz": "SLOVENSKA NACIONALNA STRANKA - SNS",
      "knaz": "SNS",
      "hcol": "4D4D4D"
    },
    {
      "ime": "Martina",
      "pri": "Strniša",
      "st": 17,
      "naz": "SOCIALNI DEMOKRATI - SD",
      "knaz": "SD",
      "hcol": "CB000D"
    },
    {
      "ime": "Bojan",
      "pri": "Bračun",
      "st": 18,
      "naz": "STRANKA ALENKE BRATUŠEK",
      "knaz": "SAB",
      "hcol": "F3808A"
    },
    {
      "ime": "Edi",
      "pri": "Einspieler",
      "st": 19,
      "naz": "VESNA - zelena stranka",
      "knaz": "VESNA",
      "hcol": "C9FFA1"
    },
    {
      "ime": "Marko",
      "pri": "Kramer",
      "st": 20,
      "naz": "ZA LJUDSTVO SLOVENIJE  - ZLS",
      "knaz": "ZLS",
      "hcol": "89AEDB"
    },
    {
      "st": 21,
      "naz": "ZOS - ZAVEZNIŠTVO OSVOBODIMO SLOVENIJO (GIBANJE ZEDINJENA SLOVENIJA - ZSI IN STRANKA SLOVENSKEGA NARODA - SSN)",
      "knaz": "ZOS",
      "hcol": "129847"
    }
  ],
  "nastavitve": {
    "timestamp": "2022-04-24T22:40:09.9634997+02:00",
    "datum": "2022-04-24T22:40:00+02:00",
    "cas_udelezba": "19:00",
    "has_udelezba": true,
    "has_rezultat": true,
    "is_final": false,
    "has_kandidati_removed": false
  }
}
